cookdir/__init__.py
cookdir/main.py
cookdir/utils.py
cookdir/recipe/data_analysis.yml
cookdir/recipe/deeplearning.yml
cookdir/recipe/deeplearning_config.tpl
cookdir/recipe/deeplearning_from_lambda.tpl
cookdir/recipe/deeplearning_trainer.tpl
cookdir/recipe/main.yml
cookdir/recipe/pypkg.yml
cookdir/recipe/pypkg_setup.tpl
cookdir-0.1.5.dist-info/LICENSE
cookdir-0.1.5.dist-info/METADATA
cookdir-0.1.5.dist-info/WHEEL
cookdir-0.1.5.dist-info/entry_points.txt
cookdir-0.1.5.dist-info/top_level.txt
cookdir-0.1.5.dist-info/RECORD
