Metadata-Version: 2.1
Name: cookdir
Version: 0.1.5
Summary: create directories by template
Home-page: https://github.com/Blockhead-yj/cookdir
Author: yjdai
Author-email: 136271877@qq.com
Classifier: Programming Language :: Python :: 3
Classifier: License :: OSI Approved :: GNU General Public License (GPL)
Classifier: Operating System :: OS Independent
Requires-Python: >=3.6
License-File: LICENSE
Requires-Dist: fire (==0.4.0)
Requires-Dist: PyYAML (==6.0)
